x_request_id_middleware/__init__.py
x_request_id_middleware/common.py
x_request_id_middleware/constants.py
x_request_id_middleware/django_middleware.py
x_request_id_middleware/fastapi_middleware.py
x_request_id_middleware/logging_config.py
x_request_id_middleware-0.2.2.dist-info/LICENSE
x_request_id_middleware-0.2.2.dist-info/METADATA
x_request_id_middleware-0.2.2.dist-info/WHEEL
x_request_id_middleware-0.2.2.dist-info/RECORD
