Metadata-Version: 2.1
Name: x-request-id-middleware
Version: 0.2.2
Summary: Library to handle request ID propagation for Django and FastAPI
Home-page: https://github.com/watchingwhileusleep/x-request-id-middleware
License: MIT
Author: WatchingWhileUSleep
Author-email: whatchingwhileusleepx@gmail.com
Requires-Python: >=3.8,<4.0
Classifier: License :: OSI Approved :: MIT License
Classifier: Programming Language :: Python :: 3
Classifier: Programming Language :: Python :: 3.8
Classifier: Programming Language :: Python :: 3.9
Classifier: Programming Language :: Python :: 3.10
Classifier: Programming Language :: Python :: 3.11
Classifier: Programming Language :: Python :: 3.12
Provides-Extra: django
Provides-Extra: fastapi
Requires-Dist: anyio (>=3.6.2,<4.0.0) ; extra == "fastapi"
Requires-Dist: django (>=4.2,<5.0) ; extra == "django"
Requires-Dist: fastapi (>=0.103.0,<0.104.0) ; extra == "fastapi"
Requires-Dist: httpx (>=0.27.0,<0.28.0) ; extra == "fastapi"
Requires-Dist: requests (>=2.32.3,<3.0.0)
Requires-Dist: sentry-sdk (>=1.16.0,<2.0.0)
Requires-Dist: starlette (>=0.27.0,<0.28.0) ; extra == "fastapi"
Project-URL: Documentation, https://github.com/watchingwhileusleep/x-request-id-middleware?tab=readme-ov-file
Project-URL: Repository, https://github.com/watchingwhileusleep/x-request-id-middleware
